{
  "appPageId" : "037cb2ea-eff2-4b4a-8f6b-dee80b19404d",
  "componentName" : "siteforce:sldsOneColLayout",
  "dataProviders" : [ ],
  "id" : "dbaa47b0-7ae1-46ec-ae72-bff6204140c2",
  "label" : "Report Detail",
  "regions" : [ {
    "id" : "2788ab30-d85a-4735-b72c-1f03866bb5c0",
    "regionName" : "header",
    "type" : "region"
  }, {
    "components" : [ {
      "componentAttributes" : {
        "recordId" : "{!recordId}"
      },
      "componentName" : "forceCommunity:reportPage",
      "id" : "7991edc9-6815-4f1a-aff5-f2f35c1ab338",
      "renderPriority" : "NEUTRAL",
      "renditionMap" : { },
      "type" : "component"
    } ],
    "id" : "410c1100-4722-42d0-ad13-03b0caafa25f",
    "regionName" : "content",
    "type" : "region"
  }, {
    "components" : [ {
      "componentAttributes" : {
        "askCommunityLabel" : "Ask a Question",
        "buttonBgColor" : "",
        "buttonBgHoverColor" : "",
        "buttonBorderColor" : "",
        "buttonRadius" : 0,
        "buttonTextColor" : "",
        "buttonTextHoverColor" : "",
        "buttonTwoBgColor" : "",
        "buttonTwoBgHoverColor" : "",
        "buttonTwoBorderColor" : "",
        "buttonTwoRadius" : 0,
        "buttonTwoTextColor" : "",
        "buttonTwoTextHoverColor" : "",
        "confirmationMessage" : "Got it!",
        "contactSupportLabel" : "Contact Support",
        "followUpPromptLabel" : "Can we close your question?",
        "headerLabel" : "Don't see what you're looking for?",
        "isAskFollowPromptEnabled" : true,
        "isIncludeArticlesEnabled" : false,
        "isIncludeDiscussionsEnabled" : true,
        "isInitialSatisfactionPromptEnabled" : true,
        "isPublisherDeflectionEnabled" : true,
        "maxSuggestions" : 5,
        "satisfactionPromptLabel" : "Did we help to answer your question?",
        "showDetails" : false,
        "showTopics" : true
      },
      "componentName" : "siteforce:napiliFooter",
      "id" : "f2da82b5-7942-4708-aa5e-3d8889c99a55",
      "renderPriority" : "NEUTRAL",
      "renditionMap" : { },
      "type" : "component"
    } ],
    "id" : "7508d048-091b-487c-afee-67d1945aa05d",
    "regionName" : "footer",
    "type" : "region"
  }, {
    "components" : [ {
      "componentAttributes" : {
        "customHeadTags" : "",
        "description" : "",
        "title" : "{!Record._Object}: {!Record._Title}"
      },
      "componentName" : "forceCommunity:seoAssistant",
      "id" : "4ed6f566-43fc-471a-9501-e74a69f8df69",
      "renditionMap" : { },
      "type" : "component"
    } ],
    "id" : "1cc88cd6-20dd-4504-b68f-3604d84f7732",
    "regionName" : "sfdcHiddenRegion",
    "type" : "region"
  } ],
  "themeLayoutType" : "Inner",
  "type" : "view",
  "viewType" : "detail-00O"
}